ds_my_snippets.py
ds_my_snippets-0.0.4.dist-info/LICENSE
ds_my_snippets-0.0.4.dist-info/METADATA
ds_my_snippets-0.0.4.dist-info/WHEEL
ds_my_snippets-0.0.4.dist-info/top_level.txt
ds_my_snippets-0.0.4.dist-info/RECORD
