Metadata-Version: 2.1
Name: ds-my-snippets
Version: 0.0.4
Summary: Snipptes of DataScience: Pandsa and VizualGraph
Home-page: UNKNOWN
Author: Rafael Morais de Assis
License: UNKNOWN
Platform: UNKNOWN
Classifier: Programming Language :: Python :: 3
Classifier: License :: OSI Approved :: MIT License
Classifier: Operating System :: OS Independent
Requires-Python: >=3.6
Requires-Dist: pandas
